atom/__init__.py
atom/auth.py
atom/client.py
atom/core.py
atom/data.py
atom/http.py
atom/http_core.py
atom/http_interface.py
atom/mock_http.py
atom/mock_http_core.py
atom/mock_service.py
atom/service.py
atom/token_store.py
atom/url.py
gdata/__init__.py
gdata/apps_property.py
gdata/auth.py
gdata/client.py
gdata/core.py
gdata/data.py
gdata/gauth.py
gdata/sample_util.py
gdata/service.py
gdata/test_config.py
gdata/test_data.py
gdata/urlfetch.py
gdata/acl/__init__.py
gdata/acl/data.py
gdata/alt/__init__.py
gdata/alt/app_engine.py
gdata/alt/appengine.py
gdata/analytics/__init__.py
gdata/analytics/client.py
gdata/analytics/data.py
gdata/analytics/service.py
gdata/apps/__init__.py
gdata/apps/apps_property_entry.py
gdata/apps/client.py
gdata/apps/data.py
gdata/apps/service.py
gdata/apps/adminsettings/__init__.py
gdata/apps/adminsettings/service.py
gdata/apps/audit/__init__.py
gdata/apps/audit/service.py
gdata/apps/emailsettings/__init__.py
gdata/apps/emailsettings/client.py
gdata/apps/emailsettings/data.py
gdata/apps/emailsettings/service.py
gdata/apps/groups/__init__.py
gdata/apps/groups/client.py
gdata/apps/groups/data.py
gdata/apps/groups/service.py
gdata/apps/migration/__init__.py
gdata/apps/migration/service.py
gdata/apps/multidomain/__init__.py
gdata/apps/multidomain/client.py
gdata/apps/multidomain/data.py
gdata/apps/organization/__init__.py
gdata/apps/organization/client.py
gdata/apps/organization/data.py
gdata/apps/organization/service.py
gdata/blogger/__init__.py
gdata/blogger/client.py
gdata/blogger/data.py
gdata/blogger/service.py
gdata/calendar/__init__.py
gdata/calendar/client.py
gdata/calendar/data.py
gdata/calendar/service.py
gdata/calendar_resource/__init__.py
gdata/calendar_resource/client.py
gdata/calendar_resource/data.py
gdata/codesearch/__init__.py
gdata/codesearch/service.py
gdata/contacts/__init__.py
gdata/contacts/client.py
gdata/contacts/data.py
gdata/contacts/service.py
gdata/contentforshopping/__init__.py
gdata/contentforshopping/client.py
gdata_python3-3.0.1.dist-info/METADATA
gdata_python3-3.0.1.dist-info/WHEEL
gdata_python3-3.0.1.dist-info/top_level.txt
gdata_python3-3.0.1.dist-info/RECORD
