Metadata-Version: 1.1
Name: gdata-python3
Version: 3.0.1
Summary: Python client library for Google data APIs
Home-page: https://github.com/dvska/gdata-python3
Author: Jeffrey Scudder
Author-email: j.s@google.com
License: Apache 2.0
Platform: UNKNOWN
Classifier: Programming Language :: Python :: 3.5
Classifier: Programming Language :: Python :: 3.6
Classifier: Programming Language :: Python :: 3.7
